bluebird_orm/__init__.py
bluebird_orm/py.typed
bluebird_orm-0.1.0.dist-info/METADATA
bluebird_orm-0.1.0.dist-info/WHEEL
bluebird_orm-0.1.0.dist-info/licenses/LICENSE
bluebird_orm-0.1.0.dist-info/RECORD
