Metadata-Version: 2.4
Name: bluebird-orm
Version: 0.1.0
Summary: Add your description here
Author-email: Alexeev Bronislav <alexeev.dev@mail.ru>
License-File: LICENSE
Requires-Python: >=3.9
Requires-Dist: psycopg2-binary>=2.9.10
Requires-Dist: requests>=2.32.4
